bssd/__init__.py
bssd/core/__init__.py
bssd/core/_bssd_handler.py
bssd/core/_immutables.py
bssd/core/_types.py
bssd/core/_util.py
bssd/core/_base/__init__.py
bssd/core/_base/behavior.py
bssd/core/_base/behavior_space.py
bssd/core/_base/boundary_lat.py
bssd/core/_base/boundary_long.py
bssd/core/_base/make_mutable.py
bssd/core/_base/relation.py
bssd/core/_base/reservation.py
bssd/core/_interfaces/__init__.py
bssd/core/_interfaces/behavior.py
bssd/core/_interfaces/behavior_space.py
bssd/core/_interfaces/boundary_lat.py
bssd/core/_interfaces/boundary_long.py
bssd/core/_interfaces/reservation.py
bssd/core/mutable/__init__.py
bssd/core/mutable/behavior.py
bssd/core/mutable/behavior_space.py
bssd/core/mutable/boundary_lat.py
bssd/core/mutable/boundary_long.py
bssd/core/mutable/relation.py
bssd/core/mutable/reservation.py
bssd_core-2025.1.dist-info/LICENSE
bssd_core-2025.1.dist-info/METADATA
bssd_core-2025.1.dist-info/WHEEL
bssd_core-2025.1.dist-info/top_level.txt
bssd_core-2025.1.dist-info/RECORD
