Metadata-Version: 2.1
Name: bssd-core
Version: 2025.1
Summary: Low level Python library for handling BSSD data within Lanelet2 maps
Author-email: "Institute of Automotive Engineering, Technical University of Darmstadt" <open-source@fzd.tu-darmstadt.de>
Maintainer-email: "Institute of Automotive Engineering, Technical University of Darmstadt" <open-source@fzd.tu-darmstadt.de>
License: Copyright 2024 Institute of Automotive Engineering (FZD), Technical University of Darmstadt
Project-URL: BSSD-Homepage, https://gitlab.com/tuda-fzd/scenery-representations-and-maps/behavior-semantic-scenery-description
Project-URL: Repository, https://gitlab.com/tuda-fzd/scenery-representations-and-maps/bssd-core
Keywords: automated driving,BSSD,OSM
Classifier: License :: OSI Approved :: MIT License
Classifier: Programming Language :: Python
Classifier: Programming Language :: Python :: 3
Requires-Python: >=3.8
License-File: LICENSE
Requires-Dist: osmium
Provides-Extra: dev
Requires-Dist: pytest; extra == "dev"
